{"dataList": [{"id": 0, "model": "이스마엘", "content": "Buyer and ... move ..."}, {"id": 1, "model": "이스마엘", "content": "They fell into his heart."}, {"id": 2, "model": "이스마엘", "content": "There is a division in his hearts."}, {"id": 3, "model": "이스마엘", "content": "He was surprised."}, {"id": 4, "model": "이스마엘", "content": "Our hearts are hunger, many cracks and spraying."}, {"id": 5, "model": "이스마엘", "content": "Before I realized, my heart's screams are full of special practices."}, {"id": 6, "model": "이스마엘", "content": "\"I got one breathing. At this level, the cause of all the bad things in the world."}, {"id": 7, "model": "이스마엘", "content": "This practice is excellent and filled with many levels ..."}, {"id": 8, "model": "이스마엘", "content": "... I don't know how I spent everyone ... and I lift the choice ..."}, {"id": 9, "model": "이스마엘", "content": "Suddenly ..."}, {"id": 10, "model": "이스마엘", "content": "I started drowning and the epthillail was also yellow."}, {"id": 11, "model": "이스마엘", "content": "I was lost."}, {"id": 12, "model": "히스클리프", "content": "……."}, {"id": 13, "model": "히스클리프", "content": "Curse, are you working inside?"}, {"id": 14, "model": "히스클리프", "content": "To go out."}, {"id": 15, "model": "이스마엘", "content": "That is a clip ... ...?"}, {"id": 16, "model": "이스마엘", "content": "When will it happen when it happens?"}, {"id": 17, "place": "Whales", "model": "히스클리프", "content": "The moment I met, I saw the same scene on scam."}, {"id": 18, "model": "히스클리프", "content": "I thought you could always get a bucket and kill the bucket."}, {"id": 19, "model": "다친이스마엘", "content": "……."}, {"id": 20, "content": "I am the weak earthquake screen."}, {"id": 21, "model": "다친이스마엘", "content": "Sorry, fast ... I can't save you ..."}, {"id": 22, "model": "퀴케그녹음", "content": "And yes."}, {"id": 23, "model": "퀴케그녹음", "content": "Think of truth and wrong."}, {"id": 24, "model": "다친이스마엘", "content": "I have to work more ... I want ..."}, {"id": 25, "model": "퀴케그녹음", "content": "Sri Akal."}, {"id": 26, "model": "퀴케그녹음", "content": "your name."}, {"id": 27, "place": "B.", "model": "이스마엘과거", "content": "Nyha could have been one of the worst places in the city, but it's a good sunset."}, {"id": 28, "model": "퀴케그과거", "content": "……."}, {"id": 29, "model": "퀴케그과거", "content": "What is your name"}, {"id": 30, "model": "이스마엘과거", "content": "Why is my name?"}, {"id": 31, "model": "퀴케그과거", "content": "Because everyone has a hair color."}, {"id": 32, "model": "퀴케그과거", "content": "Fish."}, {"id": 33, "model": "퀴케그과거", "content": "Hair color."}, {"id": 34, "model": "퀴케그과거", "content": "So if you drop the Veena, whales will be with you."}, {"id": 35, "model": "퀴케그과거", "content": "We can be a good friend."}, {"id": 36, "model": "이스마엘과거", "content": "Well ... please call me."}, {"id": 37, "place": "Whales", "model": "다친이스마엘", "content": "Call ... Ekir ..."}, {"id": 38, "model": "퀴케그녹음", "content": "……."}, {"id": 39, "content": "It is allowed without it."}, {"id": 40, "model": "다친이스마엘", "content": "……."}, {"id": 41, "content": "The Hali took the lind for several hours."}, {"id": 42, "content": "Isamas Wayne's hand and is now holy and sharp."}, {"id": 43, "model": "단테", "content": "<…….>"}, {"id": 44, "model": "다친이스마엘", "content": "You are in the way, toothpick."}, {"id": 45, "model": "다친이스마엘", "content": "Why are you doing this"}, {"id": 46, "model": "다친이스마엘", "content": "Indicates that good people are helping to reinstall?"}, {"id": 47, "model": "단테", "content": "<Do you want to know better?"}, {"id": 48, "model": "단테", "content": "<I can ... I can find a way that does not enter the bike >>"}, {"id": 49, "model": "다친이스마엘", "content": "You ... do you know?"}, {"id": 50, "model": "다친이스마엘", "content": "Do you know where you going?"}, {"id": 51, "model": "단테", "content": "<I'm looking for it."}, {"id": 52, "content": "Maybe I will call my mobile phone time time ..."}, {"id": 53, "content": "... I am looking for the infinite homeless."}, {"id": 54, "content": "To all missing people."}, {"id": 55, "content": "So I can't miss it."}, {"id": 56, "model": "단테", "content": "<History, we are all captain in our hearts."}, {"id": 57, "model": "단테", "content": "\"We work together in the same way, and sometimes residual people have taken them ... >>"}, {"id": 58, "model": "단테", "content": "<In the late everything, it should be OO leader."}, {"id": 59, "model": "단테", "content": "<Don't dare to become a pit before traveling."}]}