{"dataList": [{"id": 0, "place": "T clock", "model": "탐정홍루", "content": "Perhaps we can turn the text program into the range of thinking."}, {"id": 1, "model": "탐정홍루", "content": "Do you think I'm terrible for others?"}, {"id": 2, "model": "탐정홍루", "content": "Good ... without my family or hesitation"}, {"id": 3, "model": "단테", "content": "<... it's a very deep joke."}, {"id": 4, "model": "탐정로쟈", "content": "Criminals go through bombs directly from the bombs, but the employees are hungry to worry."}, {"id": 5, "model": "탐정료슈", "content": "Yes"}, {"id": 6, "model": "탐정로쟈", "content": "Then he cut off criminals ... he did not connect to a man and she was a long time."}, {"id": 7, "model": "탐정홍루", "content": "Or huiis van bedrizzard."}, {"id": 8, "model": "탐정홍루", "content": "Similarly, the teeth can be perfect, but this strength accepts the disease, but does not take out the ability to record the invention."}, {"id": 9, "model": "탐정료슈", "content": "Most can be \"crimes\"."}, {"id": 10, "model": "탐정로쟈", "content": "It is more than one criminal ... I want to know the company that is compatible with the correct character."}, {"id": 11, "model": "탐정로쟈", "content": "... No, I don't doubt."}, {"id": 12, "model": "T사대표", "teller": "Assistant", "title": "Tea.", "content": "Wow, this is a coincidence."}, {"id": 13, "content": "A special AvenueOn, after a particular period, after a specific period ..."}, {"id": 14, "place": "Leave the light T corporation.", "model": "T사2등급", "teller": "Collected by another employee", "title": "Tea.", "content": "Are not satisfied with the position of the nest, which a group of people ...?"}, {"id": 15, "model": "T사2등급", "teller": "Collected by another employee", "title": "Tea.", "content": "Maybe you're looking for home?"}, {"id": 16, "model": "탐정로쟈", "content": "…!"}, {"id": 17, "model": "탐정홍루", "content": "Hey, is he not the founder of the company's friend?"}, {"id": 18, "content": "Rodia closed due to phone number."}, {"id": 19, "model": "탐정로쟈", "content": "Ideal"}, {"id": 20, "model": "탐정로쟈", "content": "Here ...?"}, {"id": 21, "model": "T사2등급", "teller": "Collected by another employee", "title": "Tea.", "content": "Do you know the company?"}, {"id": 22, "model": "T사2등급", "teller": "Collected by another employee", "title": "Tea.", "content": "I heard they were late."}, {"id": 23, "model": "T사2등급", "teller": "Collected by another employee", "title": "Tea.", "content": "Employees like me have used questions about the suspected personnel of the entire nest."}, {"id": 24, "model": "T사2등급", "teller": "Collected by another employee", "title": "Tea.", "content": "This is really annoying."}, {"id": 25, "model": "탐정로쟈", "content": "So what is home?"}, {"id": 26, "model": "T사2등급", "teller": "Collected by another employee", "title": "Tea.", "content": "Different things of thieves."}, {"id": 27, "model": "T사2등급", "teller": "Collected by another employee", "title": "Tea.", "content": "Okay, I heard that researchers who do not pay for people who can't afford for time or money."}, {"id": 28, "model": "T사2등급", "teller": "Collected by another employee", "title": "Tea.", "content": "Wait for a while, everything is right?"}, {"id": 29, "model": "T사시민", "teller": "Bar", "title": "Area 20", "content": "Well ... oye, I want to leave a woman."}, {"id": 30, "model": "탐정료슈", "content": "……."}, {"id": 31, "model": "탐정로쟈", "content": "Where can we find it?"}, {"id": 32, "model": "T사2등급", "teller": "Collected by another employee", "title": "Tea.", "content": "Well, it can't be difficult."}, {"id": 33, "model": "단테", "content": "<Hangs !!> !!!!!!!"}, {"id": 34, "content": "Sudden blast Hong ..."}, {"id": 35, "model": "T사대표", "teller": "Assistant", "title": "Tea.", "content": "You talk about hell ... I can be active in their badge."}, {"id": 36, "model": "단테", "content": "<Badge activity ... \""}, {"id": 37, "model": "탐정로쟈", "content": "Wow ... noise is long, yes, tooth ..."}, {"id": 38, "model": "탐정로쟈", "content": "Let's take it."}, {"id": 39, "model": "단테", "content": "<Ghos."}, {"id": 40, "model": "T사2등급", "teller": "Collected by another employee", "title": "Tea.", "content": "Wait, can you return it?"}, {"id": 41, "model": "유로지비멤버1", "teller": "Absolutely", "title": "Area 20", "content": "Blast!"}, {"id": 42, "model": "유로지비멤버2", "teller": "An active employee", "title": "Area 20", "content": "Sat and Corporation Shin Lines ...!"}, {"id": 43, "model": "탐정로쟈", "content": "In addition, you have no time to explain, so you will not say in the future."}]}