{
  "dataList": [
    {
      "id": 0,
      "model": "이스마엘",
      "teller": "Ishmael",
      "title": "Hat",
      "content": "All!"
    }, {
      "id": 1,
      "content": "The boy is roaring and riding on top of his demons."
    }, {
      "id": 2,
      "content": "The captain is too much in the middle of the wild and light lake and fell in love."
    }, {
      "id": 3,
      "model": "이스마엘",
      "teller": "Ishmael",
      "title": "Hat",
      "content": "The captain wants to hear your throat!"
    }, {
      "id": 4,
      "model": "작살잡이",
      "content": "Six!"
    }, {
      "id": 5,
      "content": "Earlier, the first team ended in the first team tattoo."
    }, {
      "id": 6,
      "model": "이스마엘",
      "teller": "Ishmael",
      "title": "Hat",
      "content": "what else?"
    }, {
      "id": 7,
      "model": "선원들",
      "teller": "Sailor",
      "title": "B.",
      "content": "Six!"
    }, {
      "id": 8,
      "content": "The power of the driver, their mind, the peaks of the lungs, gathered from the spoil, the cow."
    }, {
      "id": 9,
      "model": "이스마엘",
      "teller": "Ishmael",
      "title": "Hat",
      "content": "You need to know where the plane is."
    }, {
      "id": 10,
      "model": "이스마엘",
      "teller": "Ishmael",
      "title": "Hat",
      "content": "We set a course to continue the bold wave!"
    }, {
      "id": 11,
      "content": "But there is no fear or pressure for the birth."
    }, {
      "id": 12,
      "content": "Only children will see."
    }, {
      "id": 13,
      "model": "이스마엘",
      "teller": "Ishmael",
      "title": "Hat",
      "content": "You also need to know what you want."
    }, {
      "id": 14,
      "model": "이스마엘",
      "teller": "Ishmael",
      "title": "Hat",
      "content": "Yes!"
    }, {
      "id": 15,
      "model": "이스마엘",
      "teller": "Ishmael",
      "title": "Hat",
      "content": "We will leave tonight!"
    }, {
      "id": 16,
      "model": "이스마엘",
      "teller": "Ishmael",
      "title": "Hat",
      "content": "What are people?"
    }, {
      "id": 17,
      "model": "선원들",
      "teller": "Sailor",
      "title": "B.",
      "content": "Son of son is filled with LOLI!"
    }, {
      "id": 18,
      "content": "This is a long and known name, but I don't care about the song."
    }, {
      "id": 19,
      "content": "But this child is slowly no history, but he emphasizes his head before he screamed."
    }, {
      "id": 20,
      "model": "이스마엘",
      "teller": "Ishmael",
      "title": "Hat",
      "content": "Error!"
    }, {
      "id": 21,
      "model": "이스마엘",
      "teller": "Ishmael",
      "title": "Hat",
      "content": "Whales are the best of your goals."
    }, {
      "id": 22,
      "model": "선원들",
      "teller": "Sailor",
      "title": "B.",
      "content": "Six!"
    }, {
      "id": 23,
      "model": "이스마엘",
      "teller": "Ishmael",
      "title": "Hat",
      "content": "The terrible limbs around us are stood and we are afraid!"
    }, {
      "id": 24,
      "model": "이스마엘",
      "teller": "Ishmael",
      "title": "Hat",
      "content": "Her dream is trying to rent our boat!"
    }, {
      "id": 25,
      "model": "선원들",
      "teller": "Sailor",
      "title": "B.",
      "content": "……."
    }, {
      "id": 26,
      "content": "no reply."
    }, {
      "id": 27,
      "content": "On the contrary, this ..."
    }, {
      "id": 28,
      "content": "... smile."
    }, {
      "id": 29,
      "content": "Everyone gets interviewed with the interviews for many interviews to get a significant value in the smile of teeth."
    }, {
      "id": 30,
      "model": "이스마엘",
      "teller": "Ishmael",
      "title": "Hat",
      "content": "I want to appear in your wings!"
    }, {
      "id": 31,
      "model": "이스마엘",
      "teller": "Ishmael",
      "title": "Hat",
      "content": "I. According to hope."
    }, {
      "id": 32,
      "model": "이스마엘",
      "teller": "Ishmael",
      "title": "Hat",
      "content": "Don't worry, follow the captain compass!"
    }, {
      "id": 33,
      "model": "이스마엘",
      "teller": "Ishmael",
      "title": "Hat",
      "content": "Finally, our overall success is designed!"
    }, {
      "id": 34,
      "model": "선원들",
      "teller": "Sailor",
      "title": "B.",
      "content": "Me, captain!"
    }, {
      "id": 35,
      "model": "일등 항해사",
      "content": "Captain, I can't wait for a storm!"
    }, {
      "id": 36,
      "content": "Another child in the cabin."
    }, {
      "id": 37,
      "content": "His eyes needed, but there was no fear."
    }, {
      "id": 38,
      "model": "이스마엘",
      "teller": "Ishmael",
      "title": "Hat",
      "content": "Time!"
    }, {
      "id": 39,
      "content": "Pico and their staff and power of heavy rains."
    }, {
      "id": 40,
      "content": "But no one surprised the Ibrow."
    }, {
      "id": 41,
      "model": "이스마엘",
      "teller": "Ishmael",
      "title": "Hat",
      "content": "The first friend!"
    }, {
      "id": 42,
      "model": "일등 항해사",
      "content": "I am looking forward to your request, captain."
    }, {
      "id": 43,
      "model": "이스마엘",
      "teller": "Ishmael",
      "title": "Hat",
      "content": "Have your instructions for another friend!"
    }, {
      "id": 44,
      "model": "이스마엘",
      "teller": "Ishmael",
      "title": "Hat",
      "content": "After the other steering -cir partner painting, join the guitar and join the neighbors!"
    }, {
      "id": 45,
      "model": "일등 항해사",
      "content": "I will accept this puzzle!"
    }, {
      "id": 46,
      "model": "이스마엘",
      "teller": "Ishmael",
      "title": "Hat",
      "content": "Port!"
    }, {
      "id": 47,
      "model": "이스마엘",
      "teller": "Ishmael",
      "title": "Hat",
      "content": "I was waiting for the opening and a number!"
    }, {
      "id": 48,
      "model": "작살잡이",
      "content": "Six!"
    }, {
      "id": 49,
      "content": "When the crew is clowns of each other, left the gooid red lake."
    }, {
      "id": 50,
      "model": "목청이 큰 선원",
      "teller": "Clouds",
      "title": "B.",
      "content": "More than one child!"
    }, {
      "id": 51,
      "model": "이스마엘",
      "teller": "Ishmael",
      "title": "Hat",
      "content": "Welcome to my boat ..."
    }, {
      "id": 52,
      "content": "When Kiroswara runs from Kiroswara Crostiva, the child is peaceful."
    }, {
      "id": 53,
      "model": "이스마엘",
      "teller": "Ishmael",
      "title": "Hat",
      "content": "Tell me your name!"
    }, {
      "id": 54,
      "model": "선원들",
      "teller": "Sailor",
      "title": "B.",
      "content": "Terrible, Captain Picor!"
    }, {
      "id": 55,
      "model": "이스마엘",
      "teller": "Ishmael",
      "title": "Hat",
      "content": "True!"
    }, {
      "id": 56,
      "content": "The child replaces a large guitar towards the whale tail."
    }, {
      "id": 57,
      "model": "이스마엘",
      "teller": "Ishmael",
      "title": "Hat",
      "content": "The dark red whales, you know my name and phone."
    }, {
      "id": 58,
      "model": "이스마엘",
      "teller": "Ishmael",
      "title": "Hat",
      "content": "You call me ... Mr."
    }, {
      "id": 59,
      "content": "In other gas lamps, the gas lamps are bright and hot because they respond to driver's hobbies."
    }, {
      "id": 60,
      "model": "이스마엘",
      "teller": "Ishmael",
      "title": "Hat",
      "content": "Half lots become your water lamp!"
    }, {
      "id": 61,
      "model": "이스마엘",
      "teller": "Ishmael",
      "title": "Hat",
      "content": "Everything comes!"
    }, {
      "id": 62,
      "model": "선원들",
      "teller": "Sailor",
      "title": "B.",
      "content": "Six!"
    }, {
      "id": 63,
      "content": "They are cooked with the eyes of staff."
    }, {
      "id": 64,
      "content": "This guy gave his beliefs with staff ..."
    }, {
      "id": 65,
      "model": "이스마엘",
      "teller": "Ishmael",
      "title": "Hat",
      "content": "All!"
    }, {
      "id": 66,
      "content": "... continues before the high whale."
    }, {
      "id": 67,
      "model": "이스마엘",
      "teller": "Ishmael",
      "title": "Hat",
      "content": "Salary!"
    }
  ]
}