{
  "dataList": [
    {
      "id": 0,
      "place": "Casino 1",
      "model": "료슈",
      "content": "If you see this magic, I can't afford it."
    }, {
      "id": 1,
      "model": "료슈",
      "content": "How much time do you spend?"
    }, {
      "id": 2,
      "model": "이스마엘",
      "content": "In the normal position, the arch is not clear support."
    }, {
      "id": 3,
      "content": "When he heard the Opposition in Mary, he turned his head and showed faith."
    }, {
      "id": 4,
      "model": "료슈",
      "content": "... it's art."
    }, {
      "id": 5,
      "model": "료슈",
      "content": "Poet, give me the sword."
    }, {
      "id": 6,
      "model": "이상",
      "content": "You can always remove it from my hand."
    }, {
      "id": 7,
      "model": "이상",
      "content": "If the sword is better than the air table."
    }, {
      "id": 8,
      "model": "료슈",
      "content": "Thank you"
    }, {
      "id": 9,
      "content": "Bringfow caught his grandfather and threw itself."
    }, {
      "id": 10,
      "content": "They made an anchor the largest and still stayed for an unknown period."
    }, {
      "id": 11,
      "content": "In fact, this expression is weak than the past, because it has become sinful."
    }, {
      "id": 12,
      "content": "We still have the best knife to cut the steel like a hot knife."
    }, {
      "id": 13,
      "content": "Of course, this behavior is smaller than rubber, but it's not a problem."
    }, {
      "id": 14,
      "content": "Everyone's eyes focus on marijuana ..."
    }, {
      "id": 15,
      "content": "Finally, all the results fell ..."
    }, {
      "id": 16,
      "model": "이상",
      "content": "That is why he became a hunt of fog."
    }, {
      "id": 17,
      "model": "각잡힌카지노경호원",
      "teller": "Hard protection",
      "title": "All companies",
      "content": "Yes?"
    }, {
      "id": 18,
      "model": "카지노경호원대장",
      "teller": "Responsible",
      "title": "All companies",
      "content": "be careful!"
    }, {
      "id": 19,
      "content": "What!"
    }, {
      "id": 20,
      "place": "Topsy-Trovi Casino 1 EF",
      "content": "Zoom destroys the earth and the great voice."
    }, {
      "id": 21,
      "content": "……"
    }, {
      "id": 22,
      "content": "And ... that's all done."
    }, {
      "id": 23,
      "content": "Nothing happened."
    }, {
      "id": 24,
      "content": "On both sides, the outdoor of the earth."
    }, {
      "id": 25,
      "model": "단테",
      "content": "<Yes, what happens?"
    }, {
      "id": 26,
      "model": "료슈",
      "content": "... Eligibility."
    }, {
      "id": 27,
      "model": "그레고르",
      "content": "Now?"
    }, {
      "id": 28,
      "model": "싱클레어",
      "content": "I'm glad because you are infected!"
    }, {
      "id": 29,
      "model": "이스마엘",
      "content": "... we have to see."
    }
  ]
}