{"dataList": [{"id": "857701_abm_success_1_1", "content": "<color=#ebcaa2>Everything is guilty</color> By%{0}Were, and,,,,,,,,,,,,,,"}, {"id": "857701_abm_success_1_2", "content": "<color=#ebcaa2>{0}</color> Enthusiastic{2} {1}Were, and,,,,,,,,,,,,,,"}, {"id": "857701_abm_failure_1_1", "content": "Place<color=#ebcaa2>{0} And and{0}</color> Unit<color=#ebcaa2>Everything is guilty</color>Then, according to the number of sinners<color=#e30000>{0} And and{0} Unit</color> To all sinners."}, {"id": "857801_success_1_1", "content": "<color=#ebcaa2>Everything is guilty</color> By%{0}Were, and,,,,,,,,,,,,,,"}, {"id": "857801_success_1_2", "content": "<color=#ebcaa2>Everything is guilty</color> <color=#80c9ff>Good{0} Stamp.</color>"}, {"id": "857801_success_1_3", "content": "<color=#ebcaa2>{0}</color> <color=#ebcaa2>Fork</color> %{2} [{1}]/% First government."}, {"id": "857801_failure_1_1", "content": "<color=#ebcaa2>[{0}]</color> <color=#ebcaa2>Fork</color> %{2} [{1}]Were, and,,,,,,,,,,,,,,"}, {"id": "857801_failure_1_2", "content": "<color=#ebcaa2>{0}</color> <color=#fe4b48>Epidemic{1} Ticket sales</color>"}, {"id": "857801_failure_1_3", "content": "<color=#ebcaa2>{0}</color> <color=#e30000>Epidemic{1} Hard power</color>"}, {"id": "857101_skinPredector_success_1_2", "content": "<color=#ebcaa2>{0}</color> <color=#ebcaa2>Fork</color> %{2} {1}Were, and,,,,,,,,,,,,,,<color=#ebcaa2>She is found.</color>"}, {"id": "857101_skinPredector_success_1_3", "content": "<color=#ebcaa2>{0}</color> <color=#ebcaa2>Fork</color> %{2} {1}/% And%{4} {3}Were, and,,,,,,,,,,,,,,<color=#ebcaa2>She is found.</color>"}, {"id": "857101_skinPredector_failure_1_1", "content": "<color=#ebcaa2>{0}</color> <color=#ebcaa2>Fork</color> %{2} {1}/% And%{4} {3}Were, and,,,,,,,,,,,,,,<color=#ebcaa2>She is found.</color>"}, {"id": "857101_skinPredector_failure_1_2", "content": "<color=#ebcaa2>Everything is guilty</color> <color=#ebcaa2>to get</color> %{1} {0}/% And%{3} {2}Were, and,,,,,,,,,,,,,,"}, {"id": "858501_soc_success_1_1", "content": "<color=#ebcaa2>{0}A part{1}</color> <color=#ebcaa2>Price is 1.5</color>"}, {"id": "858501_soc_failure_1_1", "content": "<color=#ebcaa2>[{0}]</color> <color=#e30000> I need it{1} Integration of love</color>"}, {"id": "858501_soc_failure_1_2", "content": "<color=#ebcaa2>{0}</color> <color=#fe4b48>I need it{1} Callsleylet</color>"}, {"id": "858502_soc_success_1_1", "content": "<color=#ebcaa2>{0}A part{1}</color> <color=#ebcaa2>Price is 1.5</color>"}, {"id": "858502_soc_failure_1_1", "content": "<color=#ebcaa2>[{0}]</color> <color=#e30000> I need it{1} Integration of love</color>"}, {"id": "858502_soc_failure_1_2", "content": "<color=#ebcaa2>{0}</color> <color=#fe4b48>I need it{1} Callsleylet</color>"}, {"id": "858502_soc_failure_1_3", "content": "<color=#ebcaa2>[{0}]</color> <color=#ebcaa2>Fork</color> %{2} {1}Were, and,,,,,,,,,,,,,,"}]}