{
  "dataList": [
    {
      "id": 9103,
      "content": "There is no purchase record\n\n<Open the word:\n-ਟੀ Lavin -16 ਪੱਧਰ ਦੇ ਇਨਪੁਟ ਪੱਧਰ ਦੇ ਨਾਲ, ਟੀਅਰ 2 ਲਈ ਨਵਾਂ ਸੰਪਰਕ, ਉਦਾਹਰਣ ਵਜੋਂ, ਉਦਾਹਰਣ ਵਜੋਂ, ਉਦਾਹਰਣ ਵਜੋਂ, ਉਦਾਹਰਣ ਵਜੋਂ, ਉਦਾਹਰਣ ਵਜੋਂ, ਉਦਾਹਰਣ ਵਜੋਂ, ਉਦਾਹਰਣ ਵਜੋਂ, ਉਦਾਹਰਣ ਵਜੋਂ, ਉਦਾਹਰਣ ਵਜੋਂ"
    }, {
      "id": 9108,
      "content": "There is no purchase record\n\n<Open the word:\n-ਟੀ Lavin -16 ਪੱਧਰ ਦੇ ਇਨਪੁਟ ਪੱਧਰ ਦੇ ਨਾਲ, ਟੀਅਰ 2 ਲਈ ਨਵਾਂ ਸੰਪਰਕ, ਉਦਾਹਰਣ ਵਜੋਂ, ਉਦਾਹਰਣ ਵਜੋਂ, ਉਦਾਹਰਣ ਵਜੋਂ, ਉਦਾਹਰਣ ਵਜੋਂ, ਉਦਾਹਰਣ ਵਜੋਂ, ਉਦਾਹਰਣ ਵਜੋਂ, ਉਦਾਹਰਣ ਵਜੋਂ, ਉਦਾਹਰਣ ਵਜੋਂ, ਉਦਾਹਰਣ ਵਜੋਂ"
    }, {
      "id": 9113,
      "content": "There is no purchase record\n\n<Open the word:\n-ਟੀ Lavin -16 ਪੱਧਰ ਦੇ ਇਨਪੁਟ ਪੱਧਰ ਦੇ ਨਾਲ, ਟੀਅਰ 2 ਲਈ ਨਵਾਂ ਸੰਪਰਕ, ਉਦਾਹਰਣ ਵਜੋਂ, ਉਦਾਹਰਣ ਵਜੋਂ, ਉਦਾਹਰਣ ਵਜੋਂ, ਉਦਾਹਰਣ ਵਜੋਂ, ਉਦਾਹਰਣ ਵਜੋਂ, ਉਦਾਹਰਣ ਵਜੋਂ, ਉਦਾਹਰਣ ਵਜੋਂ, ਉਦਾਹਰਣ ਵਜੋਂ, ਉਦਾਹਰਣ ਵਜੋਂ"
    }, {
      "id": 9114,
      "content": "There is no purchase record\n\n<Open the word:\n-ਟੀ Lavin -16 ਪੱਧਰ ਦੇ ਇਨਪੁਟ ਪੱਧਰ ਦੇ ਨਾਲ, ਟੀਅਰ 2 ਲਈ ਨਵਾਂ ਸੰਪਰਕ, ਉਦਾਹਰਣ ਵਜੋਂ, ਉਦਾਹਰਣ ਵਜੋਂ, ਉਦਾਹਰਣ ਵਜੋਂ, ਉਦਾਹਰਣ ਵਜੋਂ, ਉਦਾਹਰਣ ਵਜੋਂ, ਉਦਾਹਰਣ ਵਜੋਂ, ਉਦਾਹਰਣ ਵਜੋਂ, ਉਦਾਹਰਣ ਵਜੋਂ, ਉਦਾਹਰਣ ਵਜੋਂ"
    }, {
      "id": 9117,
      "content": "There is no purchase record\n\n<Open the word:\n-ਟੀ Lavin -16 ਪੱਧਰ ਦੇ ਇਨਪੁਟ ਪੱਧਰ ਦੇ ਨਾਲ, ਟੀਅਰ 2 ਲਈ ਨਵਾਂ ਸੰਪਰਕ, ਉਦਾਹਰਣ ਵਜੋਂ, ਉਦਾਹਰਣ ਵਜੋਂ, ਉਦਾਹਰਣ ਵਜੋਂ, ਉਦਾਹਰਣ ਵਜੋਂ, ਉਦਾਹਰਣ ਵਜੋਂ, ਉਦਾਹਰਣ ਵਜੋਂ, ਉਦਾਹਰਣ ਵਜੋਂ, ਉਦਾਹਰਣ ਵਜੋਂ, ਉਦਾਹਰਣ ਵਜੋਂ"
    }, {
      "id": 9119,
      "content": "There is no purchase record\n\n<Open the word:\n-ਟੀ Lavin -16 ਪੱਧਰ ਦੇ ਇਨਪੁਟ ਪੱਧਰ ਦੇ ਨਾਲ, ਟੀਅਰ 2 ਲਈ ਨਵਾਂ ਸੰਪਰਕ, ਉਦਾਹਰਣ ਵਜੋਂ, ਉਦਾਹਰਣ ਵਜੋਂ, ਉਦਾਹਰਣ ਵਜੋਂ, ਉਦਾਹਰਣ ਵਜੋਂ, ਉਦਾਹਰਣ ਵਜੋਂ, ਉਦਾਹਰਣ ਵਜੋਂ, ਉਦਾਹਰਣ ਵਜੋਂ, ਉਦਾਹਰਣ ਵਜੋਂ, ਉਦਾਹਰਣ ਵਜੋਂ"
    }, {
      "id": 9124,
      "content": "There is no purchase record\n\n<Open the word:\n-ਟੀ Lavin -16 ਪੱਧਰ ਦੇ ਇਨਪੁਟ ਪੱਧਰ ਦੇ ਨਾਲ, ਟੀਅਰ 2 ਲਈ ਨਵਾਂ ਸੰਪਰਕ, ਉਦਾਹਰਣ ਵਜੋਂ, ਉਦਾਹਰਣ ਵਜੋਂ, ਉਦਾਹਰਣ ਵਜੋਂ, ਉਦਾਹਰਣ ਵਜੋਂ, ਉਦਾਹਰਣ ਵਜੋਂ, ਉਦਾਹਰਣ ਵਜੋਂ, ਉਦਾਹਰਣ ਵਜੋਂ, ਉਦਾਹਰਣ ਵਜੋਂ, ਉਦਾਹਰਣ ਵਜੋਂ"
    }, {
      "id": 9129,
      "content": "There is no purchase record\n\n<Open the word:\n-ਟੀ Lavin -16 ਪੱਧਰ ਦੇ ਇਨਪੁਟ ਪੱਧਰ ਦੇ ਨਾਲ, ਟੀਅਰ 2 ਲਈ ਨਵਾਂ ਸੰਪਰਕ, ਉਦਾਹਰਣ ਵਜੋਂ, ਉਦਾਹਰਣ ਵਜੋਂ, ਉਦਾਹਰਣ ਵਜੋਂ, ਉਦਾਹਰਣ ਵਜੋਂ, ਉਦਾਹਰਣ ਵਜੋਂ, ਉਦਾਹਰਣ ਵਜੋਂ, ਉਦਾਹਰਣ ਵਜੋਂ, ਉਦਾਹਰਣ ਵਜੋਂ, ਉਦਾਹਰਣ ਵਜੋਂ"
    }, {
      "id": 9134,
      "content": "There is no purchase record\n\n<Open the word:\n-ਟੀ Lavin -16 ਪੱਧਰ ਦੇ ਇਨਪੁਟ ਪੱਧਰ ਦੇ ਨਾਲ, ਟੀਅਰ 2 ਲਈ ਨਵਾਂ ਸੰਪਰਕ, ਉਦਾਹਰਣ ਵਜੋਂ, ਉਦਾਹਰਣ ਵਜੋਂ, ਉਦਾਹਰਣ ਵਜੋਂ, ਉਦਾਹਰਣ ਵਜੋਂ, ਉਦਾਹਰਣ ਵਜੋਂ, ਉਦਾਹਰਣ ਵਜੋਂ, ਉਦਾਹਰਣ ਵਜੋਂ, ਉਦਾਹਰਣ ਵਜੋਂ, ਉਦਾਹਰਣ ਵਜੋਂ"
    }, {
      "id": 9139,
      "content": "There is no purchase record\n\n<Open the word:\n-ਟੀ Lavin -16 ਪੱਧਰ ਦੇ ਇਨਪੁਟ ਪੱਧਰ ਦੇ ਨਾਲ, ਟੀਅਰ 2 ਲਈ ਨਵਾਂ ਸੰਪਰਕ, ਉਦਾਹਰਣ ਵਜੋਂ, ਉਦਾਹਰਣ ਵਜੋਂ, ਉਦਾਹਰਣ ਵਜੋਂ, ਉਦਾਹਰਣ ਵਜੋਂ, ਉਦਾਹਰਣ ਵਜੋਂ, ਉਦਾਹਰਣ ਵਜੋਂ, ਉਦਾਹਰਣ ਵਜੋਂ, ਉਦਾਹਰਣ ਵਜੋਂ, ਉਦਾਹਰਣ ਵਜੋਂ"
    }, {
      "id": 9140,
      "content": "There is no purchase record\n\n<Open the word:\n-ਟੀ Lavin -16 ਪੱਧਰ ਦੇ ਇਨਪੁਟ ਪੱਧਰ ਦੇ ਨਾਲ, ਟੀਅਰ 2 ਲਈ ਨਵਾਂ ਸੰਪਰਕ, ਉਦਾਹਰਣ ਵਜੋਂ, ਉਦਾਹਰਣ ਵਜੋਂ, ਉਦਾਹਰਣ ਵਜੋਂ, ਉਦਾਹਰਣ ਵਜੋਂ, ਉਦਾਹਰਣ ਵਜੋਂ, ਉਦਾਹਰਣ ਵਜੋਂ, ਉਦਾਹਰਣ ਵਜੋਂ, ਉਦਾਹਰਣ ਵਜੋਂ, ਉਦਾਹਰਣ ਵਜੋਂ"
    }, {
      "id": 9144,
      "content": "There is no purchase record\n\n<Open the word:\n-ਟੀ Lavin -16 ਪੱਧਰ ਦੇ ਇਨਪੁਟ ਪੱਧਰ ਦੇ ਨਾਲ, ਟੀਅਰ 2 ਲਈ ਨਵਾਂ ਸੰਪਰਕ, ਉਦਾਹਰਣ ਵਜੋਂ, ਉਦਾਹਰਣ ਵਜੋਂ, ਉਦਾਹਰਣ ਵਜੋਂ, ਉਦਾਹਰਣ ਵਜੋਂ, ਉਦਾਹਰਣ ਵਜੋਂ, ਉਦਾਹਰਣ ਵਜੋਂ, ਉਦਾਹਰਣ ਵਜੋਂ, ਉਦਾਹਰਣ ਵਜੋਂ, ਉਦਾਹਰਣ ਵਜੋਂ"
    }, {
      "id": 9145,
      "content": "There is no purchase record\n\n<Open the word:\n-ਟੀ Lavin -16 ਪੱਧਰ ਦੇ ਇਨਪੁਟ ਪੱਧਰ ਦੇ ਨਾਲ, ਟੀਅਰ 2 ਲਈ ਨਵਾਂ ਸੰਪਰਕ, ਉਦਾਹਰਣ ਵਜੋਂ, ਉਦਾਹਰਣ ਵਜੋਂ, ਉਦਾਹਰਣ ਵਜੋਂ, ਉਦਾਹਰਣ ਵਜੋਂ, ਉਦਾਹਰਣ ਵਜੋਂ, ਉਦਾਹਰਣ ਵਜੋਂ, ਉਦਾਹਰਣ ਵਜੋਂ, ਉਦਾਹਰਣ ਵਜੋਂ, ਉਦਾਹਰਣ ਵਜੋਂ"
    }, {
      "id": 9149,
      "content": "There is no purchase record\n\n<Open the word:\n-ਟੀ Lavin -16 ਪੱਧਰ ਦੇ ਇਨਪੁਟ ਪੱਧਰ ਦੇ ਨਾਲ, ਟੀਅਰ 2 ਲਈ ਨਵਾਂ ਸੰਪਰਕ, ਉਦਾਹਰਣ ਵਜੋਂ, ਉਦਾਹਰਣ ਵਜੋਂ, ਉਦਾਹਰਣ ਵਜੋਂ, ਉਦਾਹਰਣ ਵਜੋਂ, ਉਦਾਹਰਣ ਵਜੋਂ, ਉਦਾਹਰਣ ਵਜੋਂ, ਉਦਾਹਰਣ ਵਜੋਂ, ਉਦਾਹਰਣ ਵਜੋਂ, ਉਦਾਹਰਣ ਵਜੋਂ"
    }, {
      "id": 9150,
      "content": "There is no purchase record\n\n<Open the word:\n-ਟੀ Lavin -16 ਪੱਧਰ ਦੇ ਇਨਪੁਟ ਪੱਧਰ ਦੇ ਨਾਲ, ਟੀਅਰ 2 ਲਈ ਨਵਾਂ ਸੰਪਰਕ, ਉਦਾਹਰਣ ਵਜੋਂ, ਉਦਾਹਰਣ ਵਜੋਂ, ਉਦਾਹਰਣ ਵਜੋਂ, ਉਦਾਹਰਣ ਵਜੋਂ, ਉਦਾਹਰਣ ਵਜੋਂ, ਉਦਾਹਰਣ ਵਜੋਂ, ਉਦਾਹਰਣ ਵਜੋਂ, ਉਦਾਹਰਣ ਵਜੋਂ, ਉਦਾਹਰਣ ਵਜੋਂ"
    }, {
      "id": 9153,
      "content": "There is no purchase record\n\n<Open the word:\n-ਟੀ Lavin -16 ਪੱਧਰ ਦੇ ਇਨਪੁਟ ਪੱਧਰ ਦੇ ਨਾਲ, ਟੀਅਰ 2 ਲਈ ਨਵਾਂ ਸੰਪਰਕ, ਉਦਾਹਰਣ ਵਜੋਂ, ਉਦਾਹਰਣ ਵਜੋਂ, ਉਦਾਹਰਣ ਵਜੋਂ, ਉਦਾਹਰਣ ਵਜੋਂ, ਉਦਾਹਰਣ ਵਜੋਂ, ਉਦਾਹਰਣ ਵਜੋਂ, ਉਦਾਹਰਣ ਵਜੋਂ, ਉਦਾਹਰਣ ਵਜੋਂ, ਉਦਾਹਰਣ ਵਜੋਂ"
    }, {
      "id": 9053,
      "content": "There is no purchase record\n\n<Open the word:\nConference group for 3 to 4 new storms, for example, existing gifts, gifts and shops unrestrained"
    }, {
      "id": 9042,
      "content": "There is no purchase record\n\n<Open the word:\nConference group for 3 to 4 new storms, for example, existing gifts, gifts and shops unrestrained"
    }, {
      "id": 9091,
      "content": "There is no purchase record\n\n<Open the word:\nConference group for 3 to 4 new storms, for example, existing gifts, gifts and shops unrestrained"
    }, {
      "id": 9033,
      "content": "There is no purchase record\n\n<Open the word:\nConference group for 3 to 4 new storms, for example, existing gifts, gifts and shops unrestrained"
    }, {
      "id": 9059,
      "content": "There is no purchase record\n\n<Open the word:\nConference group for 3 to 4 new storms, for example, existing gifts, gifts and shops unrestrained"
    }, {
      "id": 9056,
      "content": "There is no purchase record\n\n<Open the word:\nConference group for 3 to 4 new storms, for example, existing gifts, gifts and shops unrestrained"
    }, {
      "id": 9099,
      "content": "There is no purchase record\n\n<Open the word:\nConference group for 3 to 4 new storms, for example, existing gifts, gifts and shops unrestrained"
    }, {
      "id": 9104,
      "content": "There is no purchase record\n\n<Open the word:\nConference group for 3 to 4 new storms, for example, existing gifts, gifts and shops unrestrained"
    }, {
      "id": 9109,
      "content": "There is no purchase record\n\n<Open the word:\nConference group for 3 to 4 new storms, for example, existing gifts, gifts and shops unrestrained"
    }, {
      "id": 9115,
      "content": "There is no purchase record\n\n<Open the word:\nConference group for 3 to 4 new storms, for example, existing gifts, gifts and shops unrestrained"
    }, {
      "id": 9120,
      "content": "There is no purchase record\n\n<Open the word:\nConference group for 3 to 4 new storms, for example, existing gifts, gifts and shops unrestrained"
    }, {
      "id": 9125,
      "content": "There is no purchase record\n\n<Open the word:\nConference group for 3 to 4 new storms, for example, existing gifts, gifts and shops unrestrained"
    }, {
      "id": 9130,
      "content": "There is no purchase record\n\n<Open the word:\nConference group for 3 to 4 new storms, for example, existing gifts, gifts and shops unrestrained"
    }, {
      "id": 9135,
      "content": "There is no purchase record\n\n<Open the word:\nConference group for 3 to 4 new storms, for example, existing gifts, gifts and shops unrestrained"
    }, {
      "id": 9141,
      "content": "There is no purchase record\n\n<Open the word:\nConference group for 3 to 4 new storms, for example, existing gifts, gifts and shops unrestrained"
    }, {
      "id": 9146,
      "content": "There is no purchase record\n\n<Open the word:\nConference group for 3 to 4 new storms, for example, existing gifts, gifts and shops unrestrained"
    }, {
      "id": 9151,
      "content": "There is no purchase record\n\n<Open the word:\nConference group for 3 to 4 new storms, for example, existing gifts, gifts and shops unrestrained"
    }, {
      "id": 9154,
      "content": "There is no purchase record\n\n<Open the word:\nConference group for 3 to 4 new storms, for example, existing gifts, gifts and shops unrestrained"
    }, {
      "id": 9105,
      "content": "There is no purchase record\n\n<Open the word:\nConference group for 3 to 4 new storms, for example, existing gifts, gifts and shops unrestrained"
    }, {
      "id": 9110,
      "content": "There is no purchase record\n\n<Open the word:\nConference group for 3 to 4 new storms, for example, existing gifts, gifts and shops unrestrained"
    }, {
      "id": 9116,
      "content": "There is no purchase record\n\n<Open the word:\nConference group for 3 to 4 new storms, for example, existing gifts, gifts and shops unrestrained"
    }, {
      "id": 9121,
      "content": "There is no purchase record\n\n<Open the word:\nConference group for 3 to 4 new storms, for example, existing gifts, gifts and shops unrestrained"
    }, {
      "id": 9126,
      "content": "There is no purchase record\n\n<Open the word:\nConference group for 3 to 4 new storms, for example, existing gifts, gifts and shops unrestrained"
    }, {
      "id": 9131,
      "content": "There is no purchase record\n\n<Open the word:\nConference group for 3 to 4 new storms, for example, existing gifts, gifts and shops unrestrained"
    }, {
      "id": 9136,
      "content": "There is no purchase record\n\n<Open the word:\nConference group for 3 to 4 new storms, for example, existing gifts, gifts and shops unrestrained"
    }, {
      "id": 9142,
      "content": "There is no purchase record\n\n<Open the word:\nConference group for 3 to 4 new storms, for example, existing gifts, gifts and shops unrestrained"
    }, {
      "id": 9147,
      "content": "There is no purchase record\n\n<Open the word:\nConference group for 3 to 4 new storms, for example, existing gifts, gifts and shops unrestrained"
    }, {
      "id": 9152,
      "content": "There is no purchase record\n\n<Open the word:\nConference group for 3 to 4 new storms, for example, existing gifts, gifts and shops unrestrained"
    }, {
      "id": 9088,
      "content": "There is no purchase record\n\n<Open the word:\nFor example, gift."
    }, {
      "id": 9090,
      "content": "There is no purchase record\n\n<Open the word:\nFor example, gift."
    }, {
      "id": 9092,
      "content": "There is no purchase record\n\n<Open the word:\nFor example, gift."
    }, {
      "id": 9094,
      "content": "There is no purchase record\n\n<Open the word:\nFor example, gift."
    }, {
      "id": 9096,
      "content": "There is no purchase record\n\n<Open the word:\nFor example, gift."
    }, {
      "id": 9098,
      "content": "There is no purchase record\n\n<Open the word:\nFor example, gift."
    }, {
      "id": 9100,
      "content": "There is no purchase record\n\n<Open the word:\nFor example, gift."
    }, {
      "id": 9410,
      "content": "There is no purchase record\n\n<Open the word:\nFor example, gift."
    }, {
      "id": 9416,
      "content": "There is no purchase record\n\n<Open the word:\nFor example, gift."
    }, {
      "id": 9424,
      "content": "There is no purchase record\n\n<Open the word:\nFor example, gift."
    }, {
      "id": 9430,
      "content": "There is no purchase record\n\n<Open the word:\nFor example, gift."
    }, {
      "id": 9434,
      "content": "There is no purchase record\n\n<Open the word:\nFor example, gift."
    }, {
      "id": 9717,
      "content": "There is no purchase record\n\n<Open the word:\nFor example, gift."
    }, {
      "id": 9718,
      "content": "There is no purchase record\n\n<Open the word:\nFor example, gift."
    }, {
      "id": 9728,
      "content": "There is no purchase record\n\n<Open the word:\nFor example, gift."
    }, {
      "id": 9729,
      "content": "There is no purchase record\n\n<Open the word:\nFor example, gift."
    }, {
      "id": 9730,
      "content": "There is no purchase record\n\n<Open the word:\nFor example, gift."
    }, {
      "id": 9731,
      "content": "There is no purchase record\n\n<Open the word:\nFor example, gift."
    }, {
      "id": 9740,
      "content": "There is no purchase record\n\n<Open the word:\nFor example, gift."
    }, {
      "id": 9741,
      "content": "There is no purchase record\n\n<Open the word:\nFor example, gift."
    }, {
      "id": 9742,
      "content": "There is no purchase record\n\n<Open the word:\nFor example, gift."
    }, {
      "id": 9743,
      "content": "There is no purchase record\n\n<Open the word:\nFor example, gift."
    }
  ]
}